sfn_db_query_builder/__init__.py
sfn_db_query_builder/multi_database_query_builder.py
sfn_db_query_builder/config/__init__.py
sfn_db_query_builder/config/constants.py
sfn_db_query_builder/config/database_types.py
sfn_db_query_builder/core/__init__.py
sfn_db_query_builder/core/base.py
sfn_db_query_builder/core/exceptions.py
sfn_db_query_builder/core/factory.py
sfn_db_query_builder/core/interfaces.py
sfn_db_query_builder/implementations/__init__.py
sfn_db_query_builder/implementations/base.py
sfn_db_query_builder/implementations/bigquery/__init__.py
sfn_db_query_builder/implementations/bigquery/sfn_db_query_builder.py
sfn_db_query_builder/implementations/postgresql/__init__.py
sfn_db_query_builder/implementations/postgresql/sfn_db_query_builder.py
sfn_db_query_builder/implementations/redshift/__init__.py
sfn_db_query_builder/implementations/redshift/sfn_db_query_builder.py
sfn_db_query_builder/implementations/snowflake/__init__.py
sfn_db_query_builder/implementations/snowflake/sfn_db_query_builder.py
sfn_db_query_builder-2.1.dist-info/METADATA
sfn_db_query_builder-2.1.dist-info/WHEEL
sfn_db_query_builder-2.1.dist-info/top_level.txt
sfn_db_query_builder-2.1.dist-info/RECORD
