Metadata-Version: 2.4
Name: sfn_db_query_builder
Version: 2.1
Summary: Simplify SQL queries across databases
Home-page: https://github.com/stepfnAI/db_query_builder
Author: Rajesh Darak
Author-email: rajesh@stepfunction.ai
Classifier: Programming Language :: Python :: 3
Classifier: License :: OSI Approved :: MIT License
Classifier: Operating System :: OS Independent
Requires-Python: >=3.8
Requires-Dist: SQLAlchemy
Requires-Dist: snowflake-connector-python
Requires-Dist: snowflake-snowpark-python
Requires-Dist: snowflake-sqlalchemy
Requires-Dist: sqlalchemy-bigquery
Requires-Dist: sqlalchemy-redshift
Requires-Dist: redshift-connector
Requires-Dist: psycopg2-binary
Dynamic: author
Dynamic: author-email
Dynamic: classifier
Dynamic: description
Dynamic: description-content-type
Dynamic: home-page
Dynamic: requires-dist
Dynamic: requires-python
Dynamic: summary
